{
  "id": 470251843,
  "node_id": "R_kgDOHAd5Qw",
  "name": "BITB",
  "full_name": "mrd0x/BITB",
  "private": false,
  "owner": {
    "login": "mrd0x",
    "id": 28691727,
    "node_id": "MDQ6VXNlcjI4NjkxNzI3",
    "avatar_url": "https://avatars.githubusercontent.com/u/28691727?v=4",
    "gravatar_id": "",
    "url": "https://api.github.com/users/mrd0x",
    "html_url": "https://github.com/mrd0x",
    "followers_url": "https://api.github.com/users/mrd0x/followers",
    "following_url": "https://api.github.com/users/mrd0x/following{/other_user}",
    "gists_url": "https://api.github.com/users/mrd0x/gists{/gist_id}",
    "starred_url": "https://api.github.com/users/mrd0x/starred{/owner}{/repo}",
    "subscriptions_url": "https://api.github.com/users/mrd0x/subscriptions",
    "organizations_url": "https://api.github.com/users/mrd0x/orgs",
    "repos_url": "https://api.github.com/users/mrd0x/repos",
    "events_url": "https://api.github.com/users/mrd0x/events{/privacy}",
    "received_events_url": "https://api.github.com/users/mrd0x/received_events",
    "type": "User",
    "user_view_type": "public",
    "site_admin": false
  },
  "html_url": "https://github.com/mrd0x/BITB",
  "description": "Browser In The Browser (BITB) Templates",
  "fork": false,
  "url": "https://api.github.com/repos/mrd0x/BITB",
  "forks_url": "https://api.github.com/repos/mrd0x/BITB/forks",
  "keys_url": "https://api.github.com/repos/mrd0x/BITB/keys{/key_id}",
  "collaborators_url": "https://api.github.com/repos/mrd0x/BITB/collaborators{/collaborator}",
  "teams_url": "https://api.github.com/repos/mrd0x/BITB/teams",
  "hooks_url": "https://api.github.com/repos/mrd0x/BITB/hooks",
  "issue_events_url": "https://api.github.com/repos/mrd0x/BITB/issues/events{/number}",
  "events_url": "https://api.github.com/repos/mrd0x/BITB/events",
  "assignees_url": "https://api.github.com/repos/mrd0x/BITB/assignees{/user}",
  "branches_url": "https://api.github.com/repos/mrd0x/BITB/branches{/branch}",
  "tags_url": "https://api.github.com/repos/mrd0x/BITB/tags",
  "blobs_url": "https://api.github.com/repos/mrd0x/BITB/git/blobs{/sha}",
  "git_tags_url": "https://api.github.com/repos/mrd0x/BITB/git/tags{/sha}",
  "git_refs_url": "https://api.github.com/repos/mrd0x/BITB/git/refs{/sha}",
  "trees_url": "https://api.github.com/repos/mrd0x/BITB/git/trees{/sha}",
  "statuses_url": "https://api.github.com/repos/mrd0x/BITB/statuses/{sha}",
  "languages_url": "https://api.github.com/repos/mrd0x/BITB/languages",
  "stargazers_url": "https://api.github.com/repos/mrd0x/BITB/stargazers",
  "contributors_url": "https://api.github.com/repos/mrd0x/BITB/contributors",
  "subscribers_url": "https://api.github.com/repos/mrd0x/BITB/subscribers",
  "subscription_url": "https://api.github.com/repos/mrd0x/BITB/subscription",
  "commits_url": "https://api.github.com/repos/mrd0x/BITB/commits{/sha}",
  "git_commits_url": "https://api.github.com/repos/mrd0x/BITB/git/commits{/sha}",
  "comments_url": "https://api.github.com/repos/mrd0x/BITB/comments{/number}",
  "issue_comment_url": "https://api.github.com/repos/mrd0x/BITB/issues/comments{/number}",
  "contents_url": "https://api.github.com/repos/mrd0x/BITB/contents/{+path}",
  "compare_url": "https://api.github.com/repos/mrd0x/BITB/compare/{base}...{head}",
  "merges_url": "https://api.github.com/repos/mrd0x/BITB/merges",
  "archive_url": "https://api.github.com/repos/mrd0x/BITB/{archive_format}{/ref}",
  "downloads_url": "https://api.github.com/repos/mrd0x/BITB/downloads",
  "issues_url": "https://api.github.com/repos/mrd0x/BITB/issues{/number}",
  "pulls_url": "https://api.github.com/repos/mrd0x/BITB/pulls{/number}",
  "milestones_url": "https://api.github.com/repos/mrd0x/BITB/milestones{/number}",
  "notifications_url": "https://api.github.com/repos/mrd0x/BITB/notifications{?since,all,participating}",
  "labels_url": "https://api.github.com/repos/mrd0x/BITB/labels{/name}",
  "releases_url": "https://api.github.com/repos/mrd0x/BITB/releases{/id}",
  "deployments_url": "https://api.github.com/repos/mrd0x/BITB/deployments",
  "created_at": "2022-03-15T16:51:39Z",
  "updated_at": "2025-05-26T03:18:55Z",
  "pushed_at": "2024-01-26T05:20:18Z",
  "git_url": "git://github.com/mrd0x/BITB.git",
  "ssh_url": "git@github.com:mrd0x/BITB.git",
  "clone_url": "https://github.com/mrd0x/BITB.git",
  "svn_url": "https://github.com/mrd0x/BITB",
  "homepage": null,
  "size": 2085,
  "stargazers_count": 2823,
  "watchers_count": 2823,
  "language": "JavaScript",
  "has_issues": false,
  "has_projects": true,
  "has_downloads": true,
  "has_wiki": true,
  "has_pages": false,
  "has_discussions": false,
  "forks_count": 477,
  "mirror_url": null,
  "archived": false,
  "disabled": false,
  "open_issues_count": 10,
  "license": null,
  "allow_forking": true,
  "is_template": false,
  "web_commit_signoff_required": false,
  "topics": [],
  "visibility": "public",
  "forks": 477,
  "open_issues": 10,
  "watchers": 2823,
  "default_branch": "main",
  "permissions": {
    "admin": false,
    "maintain": false,
    "push": false,
    "triage": false,
    "pull": true
  },
  "temp_clone_token": "",
  "network_count": 477,
  "subscribers_count": 56
}