{
  "id": 8764239,
  "node_id": "MDEwOlJlcG9zaXRvcnk4NzY0MjM5",
  "name": "goos-by-chapter",
  "full_name": "jbalmert/goos-by-chapter",
  "private": false,
  "owner": {
    "login": "jbalmert",
    "id": 3053460,
    "node_id": "MDQ6VXNlcjMwNTM0NjA=",
    "avatar_url": "https://avatars.githubusercontent.com/u/3053460?v=4",
    "gravatar_id": "",
    "url": "https://api.github.com/users/jbalmert",
    "html_url": "https://github.com/jbalmert",
    "followers_url": "https://api.github.com/users/jbalmert/followers",
    "following_url": "https://api.github.com/users/jbalmert/following{/other_user}",
    "gists_url": "https://api.github.com/users/jbalmert/gists{/gist_id}",
    "starred_url": "https://api.github.com/users/jbalmert/starred{/owner}{/repo}",
    "subscriptions_url": "https://api.github.com/users/jbalmert/subscriptions",
    "organizations_url": "https://api.github.com/users/jbalmert/orgs",
    "repos_url": "https://api.github.com/users/jbalmert/repos",
    "events_url": "https://api.github.com/users/jbalmert/events{/privacy}",
    "received_events_url": "https://api.github.com/users/jbalmert/received_events",
    "type": "User",
    "user_view_type": "public",
    "site_admin": false
  },
  "html_url": "https://github.com/jbalmert/goos-by-chapter",
  "description": "Chapter by chapter build of the AuctionSniper application from Growing Object Oriented Software, Guided By Tests",
  "fork": false,
  "url": "https://api.github.com/repos/jbalmert/goos-by-chapter",
  "forks_url": "https://api.github.com/repos/jbalmert/goos-by-chapter/forks",
  "keys_url": "https://api.github.com/repos/jbalmert/goos-by-chapter/keys{/key_id}",
  "collaborators_url": "https://api.github.com/repos/jbalmert/goos-by-chapter/collaborators{/collaborator}",
  "teams_url": "https://api.github.com/repos/jbalmert/goos-by-chapter/teams",
  "hooks_url": "https://api.github.com/repos/jbalmert/goos-by-chapter/hooks",
  "issue_events_url": "https://api.github.com/repos/jbalmert/goos-by-chapter/issues/events{/number}",
  "events_url": "https://api.github.com/repos/jbalmert/goos-by-chapter/events",
  "assignees_url": "https://api.github.com/repos/jbalmert/goos-by-chapter/assignees{/user}",
  "branches_url": "https://api.github.com/repos/jbalmert/goos-by-chapter/branches{/branch}",
  "tags_url": "https://api.github.com/repos/jbalmert/goos-by-chapter/tags",
  "blobs_url": "https://api.github.com/repos/jbalmert/goos-by-chapter/git/blobs{/sha}",
  "git_tags_url": "https://api.github.com/repos/jbalmert/goos-by-chapter/git/tags{/sha}",
  "git_refs_url": "https://api.github.com/repos/jbalmert/goos-by-chapter/git/refs{/sha}",
  "trees_url": "https://api.github.com/repos/jbalmert/goos-by-chapter/git/trees{/sha}",
  "statuses_url": "https://api.github.com/repos/jbalmert/goos-by-chapter/statuses/{sha}",
  "languages_url": "https://api.github.com/repos/jbalmert/goos-by-chapter/languages",
  "stargazers_url": "https://api.github.com/repos/jbalmert/goos-by-chapter/stargazers",
  "contributors_url": "https://api.github.com/repos/jbalmert/goos-by-chapter/contributors",
  "subscribers_url": "https://api.github.com/repos/jbalmert/goos-by-chapter/subscribers",
  "subscription_url": "https://api.github.com/repos/jbalmert/goos-by-chapter/subscription",
  "commits_url": "https://api.github.com/repos/jbalmert/goos-by-chapter/commits{/sha}",
  "git_commits_url": "https://api.github.com/repos/jbalmert/goos-by-chapter/git/commits{/sha}",
  "comments_url": "https://api.github.com/repos/jbalmert/goos-by-chapter/comments{/number}",
  "issue_comment_url": "https://api.github.com/repos/jbalmert/goos-by-chapter/issues/comments{/number}",
  "contents_url": "https://api.github.com/repos/jbalmert/goos-by-chapter/contents/{+path}",
  "compare_url": "https://api.github.com/repos/jbalmert/goos-by-chapter/compare/{base}...{head}",
  "merges_url": "https://api.github.com/repos/jbalmert/goos-by-chapter/merges",
  "archive_url": "https://api.github.com/repos/jbalmert/goos-by-chapter/{archive_format}{/ref}",
  "downloads_url": "https://api.github.com/repos/jbalmert/goos-by-chapter/downloads",
  "issues_url": "https://api.github.com/repos/jbalmert/goos-by-chapter/issues{/number}",
  "pulls_url": "https://api.github.com/repos/jbalmert/goos-by-chapter/pulls{/number}",
  "milestones_url": "https://api.github.com/repos/jbalmert/goos-by-chapter/milestones{/number}",
  "notifications_url": "https://api.github.com/repos/jbalmert/goos-by-chapter/notifications{?since,all,participating}",
  "labels_url": "https://api.github.com/repos/jbalmert/goos-by-chapter/labels{/name}",
  "releases_url": "https://api.github.com/repos/jbalmert/goos-by-chapter/releases{/id}",
  "deployments_url": "https://api.github.com/repos/jbalmert/goos-by-chapter/deployments",
  "created_at": "2013-03-13T23:56:01Z",
  "updated_at": "2021-05-08T16:12:18Z",
  "pushed_at": "2013-04-28T00:36:42Z",
  "git_url": "git://github.com/jbalmert/goos-by-chapter.git",
  "ssh_url": "git@github.com:jbalmert/goos-by-chapter.git",
  "clone_url": "https://github.com/jbalmert/goos-by-chapter.git",
  "svn_url": "https://github.com/jbalmert/goos-by-chapter",
  "homepage": null,
  "size": 240,
  "stargazers_count": 11,
  "watchers_count": 11,
  "language": "Java",
  "has_issues": true,
  "has_projects": true,
  "has_downloads": true,
  "has_wiki": true,
  "has_pages": false,
  "has_discussions": false,
  "forks_count": 3,
  "mirror_url": null,
  "archived": false,
  "disabled": false,
  "open_issues_count": 0,
  "license": null,
  "allow_forking": true,
  "is_template": false,
  "web_commit_signoff_required": false,
  "topics": [],
  "visibility": "public",
  "forks": 3,
  "open_issues": 0,
  "watchers": 11,
  "default_branch": "master",
  "permissions": {
    "admin": false,
    "maintain": false,
    "push": false,
    "triage": false,
    "pull": true
  },
  "temp_clone_token": "",
  "network_count": 3,
  "subscribers_count": 4
}