{
  "id": 473949053,
  "node_id": "R_kgDOHD_jfQ",
  "name": "frankenphp",
  "full_name": "dunglas/frankenphp",
  "private": false,
  "owner": {
    "login": "dunglas",
    "id": 57224,
    "node_id": "MDQ6VXNlcjU3MjI0",
    "avatar_url": "https://avatars.githubusercontent.com/u/57224?v=4",
    "gravatar_id": "",
    "url": "https://api.github.com/users/dunglas",
    "html_url": "https://github.com/dunglas",
    "followers_url": "https://api.github.com/users/dunglas/followers",
    "following_url": "https://api.github.com/users/dunglas/following{/other_user}",
    "gists_url": "https://api.github.com/users/dunglas/gists{/gist_id}",
    "starred_url": "https://api.github.com/users/dunglas/starred{/owner}{/repo}",
    "subscriptions_url": "https://api.github.com/users/dunglas/subscriptions",
    "organizations_url": "https://api.github.com/users/dunglas/orgs",
    "repos_url": "https://api.github.com/users/dunglas/repos",
    "events_url": "https://api.github.com/users/dunglas/events{/privacy}",
    "received_events_url": "https://api.github.com/users/dunglas/received_events",
    "type": "User",
    "user_view_type": "public",
    "site_admin": false
  },
  "html_url": "https://github.com/dunglas/frankenphp",
  "description": "\ud83e\udddf The modern PHP app server",
  "fork": false,
  "url": "https://api.github.com/repos/dunglas/frankenphp",
  "forks_url": "https://api.github.com/repos/dunglas/frankenphp/forks",
  "keys_url": "https://api.github.com/repos/dunglas/frankenphp/keys{/key_id}",
  "collaborators_url": "https://api.github.com/repos/dunglas/frankenphp/collaborators{/collaborator}",
  "teams_url": "https://api.github.com/repos/dunglas/frankenphp/teams",
  "hooks_url": "https://api.github.com/repos/dunglas/frankenphp/hooks",
  "issue_events_url": "https://api.github.com/repos/dunglas/frankenphp/issues/events{/number}",
  "events_url": "https://api.github.com/repos/dunglas/frankenphp/events",
  "assignees_url": "https://api.github.com/repos/dunglas/frankenphp/assignees{/user}",
  "branches_url": "https://api.github.com/repos/dunglas/frankenphp/branches{/branch}",
  "tags_url": "https://api.github.com/repos/dunglas/frankenphp/tags",
  "blobs_url": "https://api.github.com/repos/dunglas/frankenphp/git/blobs{/sha}",
  "git_tags_url": "https://api.github.com/repos/dunglas/frankenphp/git/tags{/sha}",
  "git_refs_url": "https://api.github.com/repos/dunglas/frankenphp/git/refs{/sha}",
  "trees_url": "https://api.github.com/repos/dunglas/frankenphp/git/trees{/sha}",
  "statuses_url": "https://api.github.com/repos/dunglas/frankenphp/statuses/{sha}",
  "languages_url": "https://api.github.com/repos/dunglas/frankenphp/languages",
  "stargazers_url": "https://api.github.com/repos/dunglas/frankenphp/stargazers",
  "contributors_url": "https://api.github.com/repos/dunglas/frankenphp/contributors",
  "subscribers_url": "https://api.github.com/repos/dunglas/frankenphp/subscribers",
  "subscription_url": "https://api.github.com/repos/dunglas/frankenphp/subscription",
  "commits_url": "https://api.github.com/repos/dunglas/frankenphp/commits{/sha}",
  "git_commits_url": "https://api.github.com/repos/dunglas/frankenphp/git/commits{/sha}",
  "comments_url": "https://api.github.com/repos/dunglas/frankenphp/comments{/number}",
  "issue_comment_url": "https://api.github.com/repos/dunglas/frankenphp/issues/comments{/number}",
  "contents_url": "https://api.github.com/repos/dunglas/frankenphp/contents/{+path}",
  "compare_url": "https://api.github.com/repos/dunglas/frankenphp/compare/{base}...{head}",
  "merges_url": "https://api.github.com/repos/dunglas/frankenphp/merges",
  "archive_url": "https://api.github.com/repos/dunglas/frankenphp/{archive_format}{/ref}",
  "downloads_url": "https://api.github.com/repos/dunglas/frankenphp/downloads",
  "issues_url": "https://api.github.com/repos/dunglas/frankenphp/issues{/number}",
  "pulls_url": "https://api.github.com/repos/dunglas/frankenphp/pulls{/number}",
  "milestones_url": "https://api.github.com/repos/dunglas/frankenphp/milestones{/number}",
  "notifications_url": "https://api.github.com/repos/dunglas/frankenphp/notifications{?since,all,participating}",
  "labels_url": "https://api.github.com/repos/dunglas/frankenphp/labels{/name}",
  "releases_url": "https://api.github.com/repos/dunglas/frankenphp/releases{/id}",
  "deployments_url": "https://api.github.com/repos/dunglas/frankenphp/deployments",
  "created_at": "2022-03-25T09:37:54Z",
  "updated_at": "2025-05-27T13:25:46Z",
  "pushed_at": "2025-05-27T08:10:43Z",
  "git_url": "git://github.com/dunglas/frankenphp.git",
  "ssh_url": "git@github.com:dunglas/frankenphp.git",
  "clone_url": "https://github.com/dunglas/frankenphp.git",
  "svn_url": "https://github.com/dunglas/frankenphp",
  "homepage": "https://frankenphp.dev",
  "size": 4255,
  "stargazers_count": 7915,
  "watchers_count": 7915,
  "language": "Go",
  "has_issues": true,
  "has_projects": false,
  "has_downloads": true,
  "has_wiki": false,
  "has_pages": false,
  "has_discussions": true,
  "forks_count": 313,
  "mirror_url": null,
  "archived": false,
  "disabled": false,
  "open_issues_count": 171,
  "license": {
    "key": "mit",
    "name": "MIT License",
    "spdx_id": "MIT",
    "url": "https://api.github.com/licenses/mit",
    "node_id": "MDc6TGljZW5zZTEz"
  },
  "allow_forking": true,
  "is_template": false,
  "web_commit_signoff_required": false,
  "topics": [
    "caddy",
    "frankenphp",
    "go",
    "php",
    "sapi",
    "worker"
  ],
  "visibility": "public",
  "forks": 313,
  "open_issues": 171,
  "watchers": 7915,
  "default_branch": "main",
  "permissions": {
    "admin": false,
    "maintain": false,
    "push": false,
    "triage": false,
    "pull": true
  },
  "temp_clone_token": "",
  "network_count": 313,
  "subscribers_count": 72
}