{
  "id": 458907326,
  "node_id": "R_kgDOG1pevg",
  "name": "melody",
  "full_name": "yoav-lavi/melody",
  "private": false,
  "owner": {
    "login": "yoav-lavi",
    "id": 14347895,
    "node_id": "MDQ6VXNlcjE0MzQ3ODk1",
    "avatar_url": "https://avatars.githubusercontent.com/u/14347895?v=4",
    "gravatar_id": "",
    "url": "https://api.github.com/users/yoav-lavi",
    "html_url": "https://github.com/yoav-lavi",
    "followers_url": "https://api.github.com/users/yoav-lavi/followers",
    "following_url": "https://api.github.com/users/yoav-lavi/following{/other_user}",
    "gists_url": "https://api.github.com/users/yoav-lavi/gists{/gist_id}",
    "starred_url": "https://api.github.com/users/yoav-lavi/starred{/owner}{/repo}",
    "subscriptions_url": "https://api.github.com/users/yoav-lavi/subscriptions",
    "organizations_url": "https://api.github.com/users/yoav-lavi/orgs",
    "repos_url": "https://api.github.com/users/yoav-lavi/repos",
    "events_url": "https://api.github.com/users/yoav-lavi/events{/privacy}",
    "received_events_url": "https://api.github.com/users/yoav-lavi/received_events",
    "type": "User",
    "user_view_type": "public",
    "site_admin": false
  },
  "html_url": "https://github.com/yoav-lavi/melody",
  "description": "Melody is a language that compiles to regular expressions and aims to be more readable and maintainable",
  "fork": false,
  "url": "https://api.github.com/repos/yoav-lavi/melody",
  "forks_url": "https://api.github.com/repos/yoav-lavi/melody/forks",
  "keys_url": "https://api.github.com/repos/yoav-lavi/melody/keys{/key_id}",
  "collaborators_url": "https://api.github.com/repos/yoav-lavi/melody/collaborators{/collaborator}",
  "teams_url": "https://api.github.com/repos/yoav-lavi/melody/teams",
  "hooks_url": "https://api.github.com/repos/yoav-lavi/melody/hooks",
  "issue_events_url": "https://api.github.com/repos/yoav-lavi/melody/issues/events{/number}",
  "events_url": "https://api.github.com/repos/yoav-lavi/melody/events",
  "assignees_url": "https://api.github.com/repos/yoav-lavi/melody/assignees{/user}",
  "branches_url": "https://api.github.com/repos/yoav-lavi/melody/branches{/branch}",
  "tags_url": "https://api.github.com/repos/yoav-lavi/melody/tags",
  "blobs_url": "https://api.github.com/repos/yoav-lavi/melody/git/blobs{/sha}",
  "git_tags_url": "https://api.github.com/repos/yoav-lavi/melody/git/tags{/sha}",
  "git_refs_url": "https://api.github.com/repos/yoav-lavi/melody/git/refs{/sha}",
  "trees_url": "https://api.github.com/repos/yoav-lavi/melody/git/trees{/sha}",
  "statuses_url": "https://api.github.com/repos/yoav-lavi/melody/statuses/{sha}",
  "languages_url": "https://api.github.com/repos/yoav-lavi/melody/languages",
  "stargazers_url": "https://api.github.com/repos/yoav-lavi/melody/stargazers",
  "contributors_url": "https://api.github.com/repos/yoav-lavi/melody/contributors",
  "subscribers_url": "https://api.github.com/repos/yoav-lavi/melody/subscribers",
  "subscription_url": "https://api.github.com/repos/yoav-lavi/melody/subscription",
  "commits_url": "https://api.github.com/repos/yoav-lavi/melody/commits{/sha}",
  "git_commits_url": "https://api.github.com/repos/yoav-lavi/melody/git/commits{/sha}",
  "comments_url": "https://api.github.com/repos/yoav-lavi/melody/comments{/number}",
  "issue_comment_url": "https://api.github.com/repos/yoav-lavi/melody/issues/comments{/number}",
  "contents_url": "https://api.github.com/repos/yoav-lavi/melody/contents/{+path}",
  "compare_url": "https://api.github.com/repos/yoav-lavi/melody/compare/{base}...{head}",
  "merges_url": "https://api.github.com/repos/yoav-lavi/melody/merges",
  "archive_url": "https://api.github.com/repos/yoav-lavi/melody/{archive_format}{/ref}",
  "downloads_url": "https://api.github.com/repos/yoav-lavi/melody/downloads",
  "issues_url": "https://api.github.com/repos/yoav-lavi/melody/issues{/number}",
  "pulls_url": "https://api.github.com/repos/yoav-lavi/melody/pulls{/number}",
  "milestones_url": "https://api.github.com/repos/yoav-lavi/melody/milestones{/number}",
  "notifications_url": "https://api.github.com/repos/yoav-lavi/melody/notifications{?since,all,participating}",
  "labels_url": "https://api.github.com/repos/yoav-lavi/melody/labels{/name}",
  "releases_url": "https://api.github.com/repos/yoav-lavi/melody/releases{/id}",
  "deployments_url": "https://api.github.com/repos/yoav-lavi/melody/deployments",
  "created_at": "2022-02-13T19:18:21Z",
  "updated_at": "2025-05-20T11:12:03Z",
  "pushed_at": "2024-11-24T19:14:44Z",
  "git_url": "git://github.com/yoav-lavi/melody.git",
  "ssh_url": "git@github.com:yoav-lavi/melody.git",
  "clone_url": "https://github.com/yoav-lavi/melody.git",
  "svn_url": "https://github.com/yoav-lavi/melody",
  "homepage": "https://yoav-lavi.github.io/melody/book/",
  "size": 3985,
  "stargazers_count": 4673,
  "watchers_count": 4673,
  "language": "Rust",
  "has_issues": true,
  "has_projects": false,
  "has_downloads": true,
  "has_wiki": false,
  "has_pages": true,
  "has_discussions": true,
  "forks_count": 56,
  "mirror_url": null,
  "archived": false,
  "disabled": false,
  "open_issues_count": 8,
  "license": {
    "key": "apache-2.0",
    "name": "Apache License 2.0",
    "spdx_id": "Apache-2.0",
    "url": "https://api.github.com/licenses/apache-2.0",
    "node_id": "MDc6TGljZW5zZTI="
  },
  "allow_forking": true,
  "is_template": false,
  "web_commit_signoff_required": false,
  "topics": [
    "compiler",
    "language",
    "melody",
    "melodylang",
    "regex",
    "regexp",
    "regular-expression",
    "rust"
  ],
  "visibility": "public",
  "forks": 56,
  "open_issues": 8,
  "watchers": 4673,
  "default_branch": "main",
  "permissions": {
    "admin": false,
    "maintain": false,
    "push": false,
    "triage": false,
    "pull": true
  },
  "temp_clone_token": "",
  "network_count": 56,
  "subscribers_count": 16
}